arcor2_execution_rest_proxy/VERSION
arcor2_execution_rest_proxy/__init__.py
arcor2_execution_rest_proxy/exceptions.py
arcor2_execution_rest_proxy/py.typed
arcor2_execution_rest_proxy/scripts/__init__.py
arcor2_execution_rest_proxy/scripts/execution_rest_proxy.py
arcor2_execution_rest_proxy-1.2.0.dist-info/METADATA
arcor2_execution_rest_proxy-1.2.0.dist-info/WHEEL
arcor2_execution_rest_proxy-1.2.0.dist-info/entry_points.txt
arcor2_execution_rest_proxy-1.2.0.dist-info/namespace_packages.txt
arcor2_execution_rest_proxy-1.2.0.dist-info/top_level.txt
arcor2_execution_rest_proxy-1.2.0.dist-info/RECORD
