Metadata-Version: 2.1
Name: arcor2-execution-rest-proxy
Version: 1.2.0
Summary: REST Proxy for ARCOR2 Execution service.
Author: Robo@FIT
Author-email: imaterna@fit.vut.cz
License: LGPL
Classifier: Development Status :: 3 - Alpha
Classifier: Intended Audience :: Developers
Classifier: Topic :: Software Development :: Build Tools
Classifier: License :: OSI Approved :: GNU Lesser General Public License v3 (LGPLv3)
Classifier: Programming Language :: Python :: 3.11
Classifier: Natural Language :: English
Classifier: Topic :: Scientific/Engineering
Requires-Python: ==3.11.*
Requires-Dist: Flask (~=3.0.3)
Requires-Dist: arcor2-execution-data (~=1.2.0)
Requires-Dist: arcor2-runtime (~=1.3.0)
Requires-Dist: arcor2 (~=1.4.0)
Requires-Dist: dataclasses-jsonschema[apispec,fast-dateparsing,fast-validation] (~=2.16.0)
Requires-Dist: fastuuid (~=0.8.0)
Requires-Dist: sqlitedict (~=2.1.0)
Requires-Dist: websocket-client (~=1.8.0)
Requires-Dist: werkzeug (~=3.0.3)
